waffle_utils/__init__.py
waffle_utils/callback/__init__.py
waffle_utils/callback/callback.py
waffle_utils/enum/__init__.py
waffle_utils/enum/enum.py
waffle_utils/file/__init__.py
waffle_utils/file/io.py
waffle_utils/file/network.py
waffle_utils/file/search.py
waffle_utils/file/types.py
waffle_utils/hook/__init__.py
waffle_utils/hook/hook.py
waffle_utils/logger/__init__.py
waffle_utils/logger/template.py
waffle_utils/logger/time.py
waffle_utils/validator/__init__.py
waffle_utils/validator/type_validator.py
waffle_utils-1.1.0.dist-info/METADATA
waffle_utils-1.1.0.dist-info/WHEEL
waffle_utils-1.1.0.dist-info/top_level.txt
waffle_utils-1.1.0.dist-info/RECORD
