Metadata-Version: 2.1
Name: waffle_utils
Version: 1.1.0
Summary: Waffle Utils 🥛
Home-page: https://github.com/snuailab/waffle_utils
Author: SNUAILAB
Author-email: huijae.lee@snuailab.ai
License: GPL-3.0
Project-URL: Bug Reports, https://github.com/snuailab/waffle_utils/issues
Project-URL: Source, https://github.com/snuailab/waffle_utils
Keywords: machine-learning,deep-learning,vision,ML,DL,AI,YOLO,Ultralytics,SNUAILAB
Classifier: Development Status :: 3 - Alpha
Classifier: Intended Audience :: Developers
Classifier: Intended Audience :: Science/Research
Classifier: License :: OSI Approved :: GNU General Public License v3 (GPLv3)
Classifier: Programming Language :: Python :: 3.9
Classifier: Programming Language :: Python :: 3.10
Classifier: Topic :: Software Development
Classifier: Topic :: Scientific/Engineering
Classifier: Topic :: Scientific/Engineering :: Artificial Intelligence
Classifier: Topic :: Scientific/Engineering :: Image Recognition
Classifier: Operating System :: POSIX :: Linux
Requires-Python: >=3.9
Requires-Dist: natsort ==8.3.1
Requires-Dist: wget ==3.2
Requires-Dist: PyYAML ==6.0
Requires-Dist: sentry-sdk
